LICENSE.txt
MANIFEST.in
pyproject.toml
setup.py
./requirements/requirements.txt
./requirements/test_requirements.txt
perovskite_ml.egg-info/PKG-INFO
perovskite_ml.egg-info/SOURCES.txt
perovskite_ml.egg-info/dependency_links.txt
perovskite_ml.egg-info/requires.txt
perovskite_ml.egg-info/top_level.txt
regression_model/VERSION
regression_model/__init__.py
regression_model/config.yml
regression_model/pipeline.py
regression_model/train_pipeline.py
regression_model/config/__init__.py
regression_model/config/core.py
regression_model/datasets/__init__.py
regression_model/processing/__init__.py
regression_model/processing/data_manager.py
regression_model/processing/features.py
regression_model/processing/predict.py
regression_model/processing/validation.py
regression_model/trained_models/__init__.py
regression_model/trained_models/regression_model_output_v0.0.1.pkl