Metadata-Version: 2.1
Name: perovskite-ml
Version: 0.0.1
Summary: Regression model package predicting the formation energy of perovskite oxides.
Home-page: https://github.com/machinelurning/perovskite-ml
Author: machinelurning
Author-email: ml@ianmanding.net
License: BSD-3
Classifier: License :: OSI Approved :: MIT License
Classifier: Programming Language :: Python
Classifier: Programming Language :: Python :: 3
Classifier: Programming Language :: Python :: 3.6
Classifier: Programming Language :: Python :: 3.7
Classifier: Programming Language :: Python :: 3.8
Classifier: Programming Language :: Python :: 3.9
Classifier: Programming Language :: Python :: Implementation :: CPython
Classifier: Programming Language :: Python :: Implementation :: PyPy
Requires-Python: >=3.6.0
License-File: LICENSE.txt
